{
  "version": "2.0",
  "lastUpdated": "2026-05-03T08:50:31.153Z",
  "activeFeatures": [
    "lukelingo",
    "ui",
    "layout",
    "sets",
    "study"
  ],
  "primaryFeature": "lukelingo",
  "features": {
    "lukelingo": {
      "phase": "do",
      "phaseNumber": 3,
      "matchRate": null,
      "iterationCount": 0,
      "requirements": [],
      "documents": {},
      "timestamps": {
        "started": "2026-05-03T08:46:38.022Z",
        "lastUpdated": "2026-05-03T08:50:31.152Z"
      },
      "lastFile": "/Users/jcsong/codework/lukelingo/app/page.tsx"
    },
    "ui": {
      "phase": "do",
      "phaseNumber": 3,
      "matchRate": null,
      "iterationCount": 0,
      "requirements": [],
      "documents": {},
      "timestamps": {
        "started": "2026-05-03T08:47:39.137Z",
        "lastUpdated": "2026-05-03T08:47:50.156Z"
      },
      "lastFile": "/Users/jcsong/codework/lukelingo/components/ui/EmptyState.tsx"
    },
    "layout": {
      "phase": "do",
      "phaseNumber": 3,
      "matchRate": null,
      "iterationCount": 0,
      "requirements": [],
      "documents": {},
      "timestamps": {
        "started": "2026-05-03T08:47:55.499Z",
        "lastUpdated": "2026-05-03T08:50:18.560Z"
      },
      "lastFile": "/Users/jcsong/codework/lukelingo/components/layout/AppShell.tsx"
    },
    "sets": {
      "phase": "do",
      "phaseNumber": 3,
      "matchRate": null,
      "iterationCount": 0,
      "requirements": [],
      "documents": {},
      "timestamps": {
        "started": "2026-05-03T08:48:15.317Z",
        "lastUpdated": "2026-05-03T08:48:54.700Z"
      },
      "lastFile": "/Users/jcsong/codework/lukelingo/components/sets/SetList.tsx"
    },
    "study": {
      "phase": "do",
      "phaseNumber": 3,
      "matchRate": null,
      "iterationCount": 0,
      "requirements": [],
      "documents": {},
      "timestamps": {
        "started": "2026-05-03T08:49:05.621Z",
        "lastUpdated": "2026-05-03T08:49:47.627Z"
      },
      "lastFile": "/Users/jcsong/codework/lukelingo/components/study/StudySession.tsx"
    }
  },
  "pipeline": {
    "currentPhase": 1,
    "level": "Dynamic",
    "phaseHistory": []
  },
  "session": {
    "startedAt": "2026-05-03T08:40:31.256Z",
    "onboardingCompleted": false,
    "lastActivity": "2026-05-03T08:50:31.153Z"
  },
  "history": [
    {
      "timestamp": "2026-05-03T08:46:38.022Z",
      "feature": "lukelingo",
      "phase": "do",
      "action": "updated"
    },
    {
      "timestamp": "2026-05-03T08:46:49.356Z",
      "feature": "lukelingo",
      "phase": "do",
      "action": "updated"
    },
    {
      "timestamp": "2026-05-03T08:46:54.578Z",
      "feature": "lukelingo",
      "phase": "do",
      "action": "updated"
    },
    {
      "timestamp": "2026-05-03T08:47:03.196Z",
      "feature": "lukelingo",
      "phase": "do",
      "action": "updated"
    },
    {
      "timestamp": "2026-05-03T08:47:09.786Z",
      "feature": "lukelingo",
      "phase": "do",
      "action": "updated"
    },
    {
      "timestamp": "2026-05-03T08:47:21.494Z",
      "feature": "lukelingo",
      "phase": "do",
      "action": "updated"
    },
    {
      "timestamp": "2026-05-03T08:47:29.182Z",
      "feature": "lukelingo",
      "phase": "do",
      "action": "updated"
    },
    {
      "timestamp": "2026-05-03T08:47:39.137Z",
      "feature": "ui",
      "phase": "do",
      "action": "updated"
    },
    {
      "timestamp": "2026-05-03T08:47:44.956Z",
      "feature": "ui",
      "phase": "do",
      "action": "updated"
    },
    {
      "timestamp": "2026-05-03T08:47:50.156Z",
      "feature": "ui",
      "phase": "do",
      "action": "updated"
    },
    {
      "timestamp": "2026-05-03T08:47:55.499Z",
      "feature": "layout",
      "phase": "do",
      "action": "updated"
    },
    {
      "timestamp": "2026-05-03T08:48:01.673Z",
      "feature": "layout",
      "phase": "do",
      "action": "updated"
    },
    {
      "timestamp": "2026-05-03T08:48:15.317Z",
      "feature": "sets",
      "phase": "do",
      "action": "updated"
    },
    {
      "timestamp": "2026-05-03T08:48:24.336Z",
      "feature": "sets",
      "phase": "do",
      "action": "updated"
    },
    {
      "timestamp": "2026-05-03T08:48:31.558Z",
      "feature": "sets",
      "phase": "do",
      "action": "updated"
    },
    {
      "timestamp": "2026-05-03T08:48:42.578Z",
      "feature": "sets",
      "phase": "do",
      "action": "updated"
    },
    {
      "timestamp": "2026-05-03T08:48:54.700Z",
      "feature": "sets",
      "phase": "do",
      "action": "updated"
    },
    {
      "timestamp": "2026-05-03T08:49:05.621Z",
      "feature": "study",
      "phase": "do",
      "action": "updated"
    },
    {
      "timestamp": "2026-05-03T08:49:20.866Z",
      "feature": "study",
      "phase": "do",
      "action": "updated"
    },
    {
      "timestamp": "2026-05-03T08:49:26.730Z",
      "feature": "study",
      "phase": "do",
      "action": "updated"
    },
    {
      "timestamp": "2026-05-03T08:49:35.502Z",
      "feature": "study",
      "phase": "do",
      "action": "updated"
    },
    {
      "timestamp": "2026-05-03T08:49:47.627Z",
      "feature": "study",
      "phase": "do",
      "action": "updated"
    },
    {
      "timestamp": "2026-05-03T08:50:08.549Z",
      "feature": "layout",
      "phase": "do",
      "action": "updated"
    },
    {
      "timestamp": "2026-05-03T08:50:18.560Z",
      "feature": "layout",
      "phase": "do",
      "action": "updated"
    },
    {
      "timestamp": "2026-05-03T08:50:25.910Z",
      "feature": "lukelingo",
      "phase": "do",
      "action": "updated"
    },
    {
      "timestamp": "2026-05-03T08:50:31.153Z",
      "feature": "lukelingo",
      "phase": "do",
      "action": "updated"
    }
  ]
}